raindropio_mcp/__init__.py
raindropio_mcp/__main__.py
raindropio_mcp/main.py
raindropio_mcp/server.py
raindropio_mcp/auth/__init__.py
raindropio_mcp/auth/token_provider.py
raindropio_mcp/clients/__init__.py
raindropio_mcp/clients/base_client.py
raindropio_mcp/clients/client_factory.py
raindropio_mcp/clients/raindrop_client.py
raindropio_mcp/config/__init__.py
raindropio_mcp/config/settings.py
raindropio_mcp/models/__init__.py
raindropio_mcp/models/batch_payloads.py
raindropio_mcp/models/bookmark.py
raindropio_mcp/models/collection.py
raindropio_mcp/models/filter_payloads.py
raindropio_mcp/models/highlight.py
raindropio_mcp/models/import_export_payloads.py
raindropio_mcp/models/payloads.py
raindropio_mcp/models/tag.py
raindropio_mcp/models/user.py
raindropio_mcp/tools/__init__.py
raindropio_mcp/tools/account.py
raindropio_mcp/tools/batch.py
raindropio_mcp/tools/bookmarks.py
raindropio_mcp/tools/collections.py
raindropio_mcp/tools/filters.py
raindropio_mcp/tools/highlights.py
raindropio_mcp/tools/import_export.py
raindropio_mcp/tools/system.py
raindropio_mcp/tools/tags.py
raindropio_mcp/tools/tool_registry.py
raindropio_mcp/utils/__init__.py
raindropio_mcp/utils/exceptions.py
raindropio_mcp/utils/process_utils.py
raindropio_mcp-0.2.4.dist-info/METADATA
raindropio_mcp-0.2.4.dist-info/WHEEL
raindropio_mcp-0.2.4.dist-info/entry_points.txt
raindropio_mcp-0.2.4.dist-info/licenses/LICENSE
raindropio_mcp-0.2.4.dist-info/RECORD
