Metadata-Version: 2.4
Name: raindropio-mcp
Version: 0.2.4
Summary: Unofficial MCP Server for the Raindrop.io API
Author-email: Les Leslie <les@wedgwoodwebworks.com>
License-File: LICENSE
Requires-Python: >=3.13
Requires-Dist: fastmcp>=2.12.0
Requires-Dist: httpx>=0.27.0
Requires-Dist: mcp-common>=0.4.8
Requires-Dist: oneiric>=0.3.6
Requires-Dist: pydantic-settings>=2.1.0
Requires-Dist: pydantic>=2.5.0
